ipfabric_extensions/app_index/index.py
ipfabric_extensions/extensions/base_extension.py
ipfabric_extensions/extensions/reports/dora_example.py
ipfabric_extensions/extensions/reports/reports.py
ipfabric_extensions/extensions/search/global_search.py
ipfabric_extensions/main.py
ipfabric_extensions/utils/ipf_client.py
ipfabric_extensions-0.5.11.dist-info/LICENSE
ipfabric_extensions-0.5.11.dist-info/METADATA
ipfabric_extensions-0.5.11.dist-info/WHEEL
ipfabric_extensions-0.5.11.dist-info/RECORD
