Metadata-Version: 2.3
Name: ipfabric-extensions
Version: 0.5.11
Summary: 
Author: Cristian Cordero
Author-email: cristian.cordero@ipfabric.io
Requires-Python: >=3.10,<4.0
Classifier: Programming Language :: Python :: 3
Classifier: Programming Language :: Python :: 3.10
Classifier: Programming Language :: Python :: 3.11
Classifier: Programming Language :: Python :: 3.12
Classifier: Programming Language :: Python :: 3.13
Requires-Dist: ipfabric[all] (>=7.2.0,<8.0.0)
Requires-Dist: loguru (>=0.7.2,<0.8.0)
Requires-Dist: openpyxl (>=3.1.5,<4.0.0)
Requires-Dist: pandas (>=2.2.3,<3.0.0)
Requires-Dist: streamlit (>=1.39.0,<2.0.0)
